googlechatbot/__init__.py
googlechatbot/chat_bot.py
googlechatbot/chat_card.py
googlechatbot-1.2.2.dist-info/LICENSE
googlechatbot-1.2.2.dist-info/METADATA
googlechatbot-1.2.2.dist-info/WHEEL
googlechatbot-1.2.2.dist-info/top_level.txt
googlechatbot-1.2.2.dist-info/RECORD
