Metadata-Version: 2.1
Name: googlechatbot
Version: 1.2.2
Summary: A small package to simplify the creation of Google Chat Bots
Home-page: https://github.com/javicv/googlechatbot
Author: Javier Collado
Author-email: javicv@gmail.com
License: Apache License 2.0
License-File: LICENSE
Requires-Dist: requests
